hepynet/__init__.py
hepynet/common/__init__.py
hepynet/common/common_utils.py
hepynet/common/config_default.py
hepynet/common/config_utils.py
hepynet/common/hepy_type.py
hepynet/data_io/__init__.py
hepynet/data_io/array_utils.py
hepynet/data_io/feed_box.py
hepynet/data_io/numpy_io.py
hepynet/evaluate/__init__.py
hepynet/evaluate/evaluate_utils.py
hepynet/evaluate/importance.py
hepynet/evaluate/kinematics.py
hepynet/evaluate/metrics.py
hepynet/evaluate/mva_scores.py
hepynet/evaluate/significance.py
hepynet/evaluate/train_history.py
hepynet/main/__init__.py
hepynet/main/execute.py
hepynet/main/job_executor.py
hepynet/main/job_utils.py
hepynet/train/__init__.py
hepynet/train/evaluate.py
hepynet/train/hep_model.py
hepynet/train/train_utils.py
hepynet-0.4.2.dist-info/LICENSE.txt
hepynet-0.4.2.dist-info/METADATA
hepynet-0.4.2.dist-info/WHEEL
hepynet-0.4.2.dist-info/entry_points.txt
hepynet-0.4.2.dist-info/top_level.txt
hepynet-0.4.2.dist-info/RECORD
