Metadata-Version: 2.1
Name: hepynet
Version: 0.4.2
Summary: High energy physics, python based, neural network framework
Home-page: https://github.com/StarPrecursor/hepynet
Author: Zhe Yang
Author-email: starprecursor@gmail.com
License: UNKNOWN
Platform: UNKNOWN
Classifier: Programming Language :: Python :: 3
Classifier: License :: OSI Approved :: MIT License
Classifier: Operating System :: OS Independent
Requires-Python: <3.9,>=3.8
License-File: LICENSE.txt
Requires-Dist: tensorflow (==2.2.0)
Requires-Dist: tensorboard
Requires-Dist: keras (==2.3.0)
Requires-Dist: ray (==1.3.0)
Requires-Dist: ray[default]
Requires-Dist: ray[tune]
Requires-Dist: numpy (>=1.18.0)
Requires-Dist: pandas (>=1.2.0)
Requires-Dist: wrapt (<1.12.0)
Requires-Dist: ax-platform
Requires-Dist: sqlalchemy
Requires-Dist: hyperopt
Requires-Dist: HEBO
Requires-Dist: GitPython
Requires-Dist: pyarrow
Requires-Dist: scikit-learn
Requires-Dist: atlas-mpl-style
Requires-Dist: matplotlib
Requires-Dist: seaborn
Requires-Dist: black
Requires-Dist: packaging
